{
    "stocks": [
        {
            "ticker": " GME",
            "count": 75
        },
        {
            "ticker": " AMC",
            "count": 38
        },
        {
            "ticker": " MRK",
            "count": 27
        },
        {
            "ticker": " AMD",
            "count": 22
        },
        {
            "ticker": " SDC",
            "count": 20
        },
        {
            "ticker": " CLOV",
            "count": 16
        },
        {
            "ticker": " MSFT",
            "count": 14
        },
        {
            "ticker": " BBBY",
            "count": 13
        },
        {
            "ticker": " TSLA",
            "count": 12
        },
        {
            "ticker": " AAPL",
            "count": 10
        },
        {
            "ticker": " PLTR",
            "count": 8
        },
        {
            "ticker": " CRSR",
            "count": 8
        },
        {
            "ticker": " BNTX",
            "count": 8
        },
        {
            "ticker": " UPST",
            "count": 8
        },
        {
            "ticker": " NKE",
            "count": 8
        },
        {
            "ticker": " SNDL",
            "count": 7
        },
        {
            "ticker": " MRNA",
            "count": 7
        },
        {
            "ticker": " PFE",
            "count": 7
        },
        {
            "ticker": " CLF",
            "count": 7
        },
        {
            "ticker": " DTE",
            "count": 7
        },
        {
            "ticker": " NYC",
            "count": 7
        },
        {
            "ticker": " GOOG",
            "count": 6
        },
        {
            "ticker": " ROKU",
            "count": 6
        },
        {
            "ticker": " DLTR",
            "count": 6
        },
        {
            "ticker": " MSM",
            "count": 6
        },
        {
            "ticker": " BTU",
            "count": 5
        },
        {
            "ticker": " BABA",
            "count": 5
        },
        {
            "ticker": " AMZN",
            "count": 5
        },
        {
            "ticker": " NVDA",
            "count": 5
        },
        {
            "ticker": " SOFI",
            "count": 5
        },
        {
            "ticker": " THC",
            "count": 5
        },
        {
            "ticker": " FAMI",
            "count": 5
        },
        {
            "ticker": " CIA",
            "count": 5
        },
        {
            "ticker": " WKHS",
            "count": 4
        },
        {
            "ticker": " OCGN",
            "count": 4
        },
        {
            "ticker": " RIOT",
            "count": 4
        },
        {
            "ticker": " SKLZ",
            "count": 4
        },
        {
            "ticker": " GDP",
            "count": 4
        },
        {
            "ticker": " BTO",
            "count": 4
        },
        {
            "ticker": " ABBV",
            "count": 4
        },
        {
            "ticker": " WPG",
            "count": 4
        },
        {
            "ticker": " PDAC",
            "count": 3
        },
        {
            "ticker": " LMFA",
            "count": 3
        },
        {
            "ticker": " SAVA",
            "count": 3
        },
        {
            "ticker": " NAKD",
            "count": 3
        },
        {
            "ticker": " SOS",
            "count": 3
        },
        {
            "ticker": " LGL",
            "count": 3
        },
        {
            "ticker": " STRO",
            "count": 3
        },
        {
            "ticker": " INTC",
            "count": 3
        },
        {
            "ticker": " XOM",
            "count": 3
        },
        {
            "ticker": " CAT",
            "count": 3
        },
        {
            "ticker": " DPZ",
            "count": 3
        },
        {
            "ticker": " VIAC",
            "count": 3
        },
        {
            "ticker": " INSI",
            "count": 3
        },
        {
            "ticker": " TGT",
            "count": 3
        },
        {
            "ticker": " XLRN",
            "count": 3
        },
        {
            "ticker": " CEI",
            "count": 3
        },
        {
            "ticker": " VALE",
            "count": 3
        },
        {
            "ticker": " RKT",
            "count": 3
        },
        {
            "ticker": " AEZS",
            "count": 3
        },
        {
            "ticker": " TTOO",
            "count": 3
        },
        {
            "ticker": " TDA",
            "count": 3
        },
        {
            "ticker": " ATNF",
            "count": 3
        },
        {
            "ticker": " PLT",
            "count": 2
        },
        {
            "ticker": " AQMS",
            "count": 2
        },
        {
            "ticker": " HCA",
            "count": 2
        },
        {
            "ticker": " TEVA",
            "count": 2
        },
        {
            "ticker": " RETA",
            "count": 2
        },
        {
            "ticker": " PDD",
            "count": 2
        },
        {
            "ticker": " BIDU",
            "count": 2
        },
        {
            "ticker": " ALGN",
            "count": 2
        },
        {
            "ticker": " NVAX",
            "count": 2
        },
        {
            "ticker": " ROOT",
            "count": 2
        },
        {
            "ticker": " INVE",
            "count": 2
        },
        {
            "ticker": " GMED",
            "count": 2
        },
        {
            "ticker": " SOL",
            "count": 2
        },
        {
            "ticker": " STON",
            "count": 2
        },
        {
            "ticker": " EXPE",
            "count": 2
        },
        {
            "ticker": " MIST",
            "count": 2
        },
        {
            "ticker": " BAM",
            "count": 2
        },
        {
            "ticker": " VALU",
            "count": 2
        },
        {
            "ticker": " NHS",
            "count": 2
        },
        {
            "ticker": " TSM",
            "count": 2
        },
        {
            "ticker": " PACB",
            "count": 2
        },
        {
            "ticker": " AGC",
            "count": 2
        },
        {
            "ticker": " CROX",
            "count": 2
        },
        {
            "ticker": " AMG",
            "count": 2
        },
        {
            "ticker": " API",
            "count": 2
        },
        {
            "ticker": " FCX",
            "count": 2
        },
        {
            "ticker": " REG",
            "count": 2
        },
        {
            "ticker": " TRGP",
            "count": 2
        },
        {
            "ticker": " NSA",
            "count": 2
        },
        {
            "ticker": " WMT",
            "count": 2
        },
        {
            "ticker": " BASI",
            "count": 2
        },
        {
            "ticker": " YELP",
            "count": 2
        },
        {
            "ticker": " SAIL",
            "count": 2
        },
        {
            "ticker": " NGL",
            "count": 2
        },
        {
            "ticker": " SNAP",
            "count": 2
        },
        {
            "ticker": " ACI",
            "count": 2
        },
        {
            "ticker": " CCXI",
            "count": 2
        },
        {
            "ticker": " RVNC",
            "count": 2
        },
        {
            "ticker": " PSTH",
            "count": 2
        },
        {
            "ticker": " CVS",
            "count": 2
        },
        {
            "ticker": " MTD",
            "count": 2
        },
        {
            "ticker": " IPA",
            "count": 2
        },
        {
            "ticker": " TIGR",
            "count": 2
        },
        {
            "ticker": " JPM",
            "count": 2
        },
        {
            "ticker": " IBKR",
            "count": 2
        },
        {
            "ticker": " CRTX",
            "count": 2
        },
        {
            "ticker": " FATE",
            "count": 2
        },
        {
            "ticker": " BODY",
            "count": 2
        },
        {
            "ticker": " GOGO",
            "count": 2
        },
        {
            "ticker": " GPS",
            "count": 2
        },
        {
            "ticker": " STIM",
            "count": 2
        },
        {
            "ticker": " TRIL",
            "count": 2
        },
        {
            "ticker": " UNIT",
            "count": 2
        },
        {
            "ticker": " IRBT",
            "count": 2
        },
        {
            "ticker": " BCRX",
            "count": 2
        },
        {
            "ticker": " CLX",
            "count": 2
        },
        {
            "ticker": " ITUB",
            "count": 2
        },
        {
            "ticker": " WWE",
            "count": 2
        },
        {
            "ticker": " SSD",
            "count": 2
        },
        {
            "ticker": " TWLO",
            "count": 2
        },
        {
            "ticker": " INVA",
            "count": 2
        },
        {
            "ticker": " NKLA",
            "count": 2
        },
        {
            "ticker": " OGS",
            "count": 2
        },
        {
            "ticker": " PRTA",
            "count": 2
        },
        {
            "ticker": " MSD",
            "count": 2
        },
        {
            "ticker": " PROV",
            "count": 2
        },
        {
            "ticker": " SEDG",
            "count": 2
        },
        {
            "ticker": " HCAT",
            "count": 2
        },
        {
            "ticker": " CMG",
            "count": 2
        },
        {
            "ticker": " FANG",
            "count": 2
        },
        {
            "ticker": " STC",
            "count": 2
        },
        {
            "ticker": " ASML",
            "count": 2
        },
        {
            "ticker": " GOED",
            "count": 2
        },
        {
            "ticker": " GOEV",
            "count": 2
        },
        {
            "ticker": " OXY",
            "count": 2
        },
        {
            "ticker": " AMAT",
            "count": 2
        },
        {
            "ticker": " REGN",
            "count": 2
        },
        {
            "ticker": " EBAY",
            "count": 2
        },
        {
            "ticker": " AAWW",
            "count": 2
        },
        {
            "ticker": " RES",
            "count": 2
        },
        {
            "ticker": " SPOK",
            "count": 2
        },
        {
            "ticker": " SPRT",
            "count": 2
        },
        {
            "ticker": " BAC",
            "count": 2
        },
        {
            "ticker": " PDT",
            "count": 2
        },
        {
            "ticker": " KOSS",
            "count": 2
        },
        {
            "ticker": " COO",
            "count": 2
        },
        {
            "ticker": " SILV",
            "count": 2
        },
        {
            "ticker": " ACB",
            "count": 2
        },
        {
            "ticker": " RIO",
            "count": 2
        },
        {
            "ticker": " CBD",
            "count": 2
        },
        {
            "ticker": " MVIS",
            "count": 2
        },
        {
            "ticker": " GWRS",
            "count": 2
        },
        {
            "ticker": " CORR",
            "count": 2
        },
        {
            "ticker": " ABC",
            "count": 2
        }
    ],
    "num_posts": 160,
    "num_comments": 7387,
    "datetime": "October 02 2021 at 14:16 EST"
}